[
    { "time": "08:30 - 19:00", "day": "Пн", "className": "ТЕСТ", "instructor": "Фамилия2 Имя2" },
    { "time": "15:00 - 16:00", "day": "Вт", "className": "ТЕСТ", "instructor": "Фамилия Имя" },
    { "time": "11:30 - 16:00", "day": "Чт", "className": "ТЕСТ", "instructor": "Фамилия Имя" },
    { "time": "11:30 - 16:00", "day": "Чт", "className": "ТЕСТ", "instructor": "Фамилия Имя" },
    { "time": "09:00 - 12:00", "day": "Вс", "className": "ТЕСТ", "instructor": "Фамилия Имя" },
    { "time": "11:00 - 14:00", "day": "Вт", "className": "Длинное название названиеназвание", "instructor": "Фамилия Имя" },
    { "time": "11:00 - 11:30", "day": "Пт", "className": "Длинное название названиеназвание", "instructor": "Фамилия Имя" },
    { "time": "12:00 - 14:30", "day": "Пт", "className": "Длинное название названиеназвание", "instructor": "Фамилия Имя" }
]